{
	"configurations" : 
	[
		{
			"directories" : 
			[
				{
					"build" : ".",
					"jsonFile" : "directory-.-Debug-f5ebdc15457944623624.json",
					"minimumCMakeVersion" : 
					{
						"string" : "3.21"
					},
					"projectIndex" : 0,
					"source" : ".",
					"targetIndexes" : 
					[
						0
					]
				}
			],
			"name" : "Debug",
			"projects" : 
			[
				{
					"directoryIndexes" : 
					[
						0
					],
					"name" : "CarrosDB",
					"targetIndexes" : 
					[
						0
					]
				}
			],
			"targets" : 
			[
				{
					"directoryIndex" : 0,
					"id" : "CarrosDB::@6890427a1f51a3e7e1df",
					"jsonFile" : "target-CarrosDB-Debug-1a3e73daa333946de016.json",
					"name" : "CarrosDB",
					"projectIndex" : 0
				}
			]
		}
	],
	"kind" : "codemodel",
	"paths" : 
	{
		"build" : "/home/draco/Desktop/PA/P2/CarrosDB/cmake-build-debug",
		"source" : "/home/draco/Desktop/PA/P2/CarrosDB"
	},
	"version" : 
	{
		"major" : 2,
		"minor" : 3
	}
}
